appmode_jupyterlab/__init__.py
appmode_jupyterlab/_version.py
appmode_jupyterlab-1.0.0.data/data/share/jupyter/labextensions/@osscar/appmode-jupyterlab/package.json
appmode_jupyterlab-1.0.0.data/data/share/jupyter/labextensions/@osscar/appmode-jupyterlab/schemas/@osscar/appmode-jupyterlab/package.json.orig
appmode_jupyterlab-1.0.0.data/data/share/jupyter/labextensions/@osscar/appmode-jupyterlab/schemas/@osscar/appmode-jupyterlab/plugin.json
appmode_jupyterlab-1.0.0.data/data/share/jupyter/labextensions/@osscar/appmode-jupyterlab/static/266.6fcbbb1c8abde8870a5f.js
appmode_jupyterlab-1.0.0.data/data/share/jupyter/labextensions/@osscar/appmode-jupyterlab/static/631.8dd6ec624e0898917cc1.js
appmode_jupyterlab-1.0.0.data/data/share/jupyter/labextensions/@osscar/appmode-jupyterlab/static/remoteEntry.96fb447ba066217ed59a.js
appmode_jupyterlab-1.0.0.data/data/share/jupyter/labextensions/@osscar/appmode-jupyterlab/static/style.js
appmode_jupyterlab-1.0.0.data/data/share/jupyter/labextensions/@osscar/appmode-jupyterlab/static/third-party-licenses.json
appmode_jupyterlab-1.0.0.data/data/share/jupyter/labextensions/@osscar/appmode-jupyterlab/install.json
appmode_jupyterlab-1.0.0.data/data/share/jupyter/lab/schemas/@jupyter-appmode/jupyterlab-preview/plugin.json
appmode_jupyterlab-1.0.0.dist-info/METADATA
appmode_jupyterlab-1.0.0.dist-info/WHEEL
appmode_jupyterlab-1.0.0.dist-info/licenses/LICENSE
appmode_jupyterlab-1.0.0.dist-info/RECORD
