Metadata-Version: 2.3
Name: appmode-jupyterlab
Version: 1.0.0
Dynamic: Keywords
Summary: A JupyterLab extension for Appmode.
Project-URL: Homepage, https://github.com/osscar-org/appmode-jupyterlab
Project-URL: Bug Tracker, https://github.com/osscar-org/appmode-jupyterlab/issues
Project-URL: Repository, https://github.com/osscar-org/appmode-jupyterlab.git
Author: Dou Du
License: BSD 3-Clause License
License-File: LICENSE
Classifier: Framework :: Jupyter
Classifier: Framework :: Jupyter :: JupyterLab
Classifier: Framework :: Jupyter :: JupyterLab :: 4
Classifier: Framework :: Jupyter :: JupyterLab :: Extensions
Classifier: Framework :: Jupyter :: JupyterLab :: Extensions :: Prebuilt
Classifier: License :: OSI Approved :: BSD License
Classifier: Programming Language :: Python
Classifier: Programming Language :: Python :: 3
Classifier: Programming Language :: Python :: 3.8
Classifier: Programming Language :: Python :: 3.9
Classifier: Programming Language :: Python :: 3.10
Classifier: Programming Language :: Python :: 3.11
Classifier: Programming Language :: Python :: 3.12
Requires-Python: >=3.8
Requires-Dist: appmode>=0.10
Requires-Dist: jupyterlab>=4
